xsection/__init__.py
xsection/__main__.py
xsection/_base.py
xsection/_interpolate.py
xsection/_io.py
xsection/_tests.py
xsection/_types.py
xsection/visuals.py
xsection/warping.py
xsection/analysis/__init__.py
xsection/analysis/interaction.py
xsection/analysis/linearize.py
xsection/analysis/plastic.py
xsection/analysis/test.py
xsection/analysis/warping.py
xsection/annulus/__init__.py
xsection/composite/__init__.py
xsection/composite/_meshing.py
xsection/concrete/fiberGenerate.py
xsection/concrete/sectionFiberMain.py
xsection/experimental/fedeas.py
xsection/experimental/plate.py
xsection/library/__init__.py
xsection/library/_ashto.py
xsection/library/_girder.py
xsection/library/_rebar.py
xsection/library/_simple.py
xsection/polygon/__init__.py
xsection-0.0.24.dist-info/METADATA
xsection-0.0.24.dist-info/WHEEL
xsection-0.0.24.dist-info/entry_points.txt
xsection-0.0.24.dist-info/top_level.txt
xsection-0.0.24.dist-info/RECORD
