Metadata-Version: 2.4
Name: xsection
Version: 0.0.24
Summary: Analysis of structural cross sections
Author-email: "Claudio M. Perez" <50180406+claudioperez@users.noreply.github.com>
Project-URL: Home, https://fedeas.net
Keywords: cross section,structural engineering,structural analysis,xara,fedeas
Classifier: Development Status :: 2 - Pre-Alpha
Classifier: Intended Audience :: Science/Research
Classifier: Intended Audience :: Developers
Classifier: Programming Language :: Python
Classifier: Programming Language :: Python :: 3
Classifier: Programming Language :: Python :: 3.8
Classifier: Programming Language :: Python :: 3.9
Classifier: Programming Language :: Python :: 3.10
Classifier: Programming Language :: Python :: 3.11
Classifier: Programming Language :: Python :: 3.12
Classifier: Programming Language :: Python :: 3 :: Only
Classifier: Topic :: Software Development
Classifier: Topic :: Scientific/Engineering
Classifier: Operating System :: Microsoft :: Windows
Classifier: Operating System :: POSIX
Classifier: Operating System :: Unix
Classifier: Operating System :: MacOS
Requires-Dist: numpy
Requires-Dist: shps>=0.0.30
Requires-Dist: veux>=0.0.40
Requires-Dist: xara>=0.0.8
Requires-Dist: opensees>=0.1.22
Requires-Dist: cytriangle
Requires-Dist: meshio
